acme/__init__.py
acme/__main__.py
acme/commands.py
acme/expections.py
acme/files.py
acme/utils.py
acme/data/__init__.py
acme/data/constants.py
acme/data/employees.txt
acme/data/rates.py
acme/data/shiftwork.py
acme/domain/__init__.py
acme/domain/day.py
acme/domain/employee.py
acme/domain/shift.py
acme/domain/working_hours.py
tests/__init__.py
tests/test_commands.py
tests/test_exceptions.py
tests/test_files.py
tests/test_utils.py
tests/domain/__init__.py
tests/domain/test_day.py
tests/domain/test_employee.py
tests/domain/test_working_hours.py
acme_exercise-0.0.6.dist-info/LICENSE
acme_exercise-0.0.6.dist-info/METADATA
acme_exercise-0.0.6.dist-info/WHEEL
acme_exercise-0.0.6.dist-info/entry_points.txt
acme_exercise-0.0.6.dist-info/top_level.txt
acme_exercise-0.0.6.dist-info/RECORD
