Metadata-Version: 2.1
Name: acme-exercise
Version: 0.0.6
Summary: Console app to calculate the total that the company has to pay an employee.
Home-page: https://github.com/israteneda/acme
Author: Israel Teneda
Author-email: israteneda@gmail.com
License: MIT
Project-URL: Homepage, https://github.com/israteneda/acme
Project-URL: Source Code, https://github.com/israteneda/acme
Platform: UNKNOWN
Classifier: Programming Language :: Python :: 3
Classifier: License :: OSI Approved :: MIT License
Requires-Python: >=3.7
